<?xml version="1.0" encoding="UTF-8"?>
<metadata xml:lang="en"><Esri><CreaDate>20111018</CreaDate><CreaTime>10145800</CreaTime><ArcGISFormat>1.0</ArcGISFormat><SyncOnce>TRUE</SyncOnce><DataProperties><lineage><Process ToolSource="C:\Program Files (x86)\ArcGIS\Desktop10.0\ArcToolbox\Toolboxes\Data Management Tools.tbx\CalculateField" Date="20111018" Time="101458">CalculateField hr20070701qb_eco_geo_final_nm Source "Roelfsema University of Queensland Australia" VB #</Process><Process ToolSource="C:\Program Files (x86)\ArcGIS\Desktop10.0\ArcToolbox\Toolboxes\Data Management Tools.tbx\CalculateField" Date="20111018" Time="101603">CalculateField hr20070701qb_eco_geo_final_nm Method "Obeject Based Quickbird and photo transects" VB #</Process><Process ToolSource="C:\Program Files (x86)\ArcGIS\Desktop10.0\ArcToolbox\Toolboxes\Data Management Tools.tbx\CalculateField" Date="20111018" Time="101819">CalculateField hr20070701qb_eco_geo_final_nm Publicatio "Phinn, Roelfsema and Mumby 2011, Remote Sensing of Environments" VB #</Process><Process ToolSource="C:\Program Files (x86)\ArcGIS\Desktop10.0\ArcToolbox\Toolboxes\Data Management Tools.tbx\CalculateField" Date="20111018" Time="102139">CalculateField hr20070701qb_eco_geo_final_nm Publicatio "PhinnRoelfsemaMumby2011 International Journal of Remote Sensings" VB #</Process><Process ToolSource="C:\Program Files (x86)\ArcGIS\Desktop10.0\ArcToolbox\Toolboxes\Data Management Tools.tbx\CalculateField" Date="20111018" Time="102206">CalculateField hr20070701qb_eco_geo_final_nm Publicatio "PhinnRoelfsemaMumby2011 Int. Jr of Remote Sensings" VB #</Process></lineage></DataProperties></Esri></metadata>
